shp_core/__init__.py
shp_core/adapter.py
shp_core/crypto.py
shp_core/exceptions.py
shp_core/license.py
shp_core/memory.py
shp_core/network.py
shp_core/node.py
shp_core/protocol.py
silent_hope_protocol-1.1.0.dist-info/METADATA
silent_hope_protocol-1.1.0.dist-info/WHEEL
silent_hope_protocol-1.1.0.dist-info/entry_points.txt
silent_hope_protocol-1.1.0.dist-info/licenses/LICENSE.md
silent_hope_protocol-1.1.0.dist-info/RECORD
