Metadata-Version: 2.4
Name: silent-hope-protocol
Version: 1.1.0
Summary: The TCP/IP of Artificial Intelligence. Not an API. A Protocol.
Project-URL: Homepage, https://github.com/silentnoisehun/Silent-Hope-Protocol
Project-URL: Documentation, https://github.com/silentnoisehun/Silent-Hope-Protocol#readme
Project-URL: Repository, https://github.com/silentnoisehun/Silent-Hope-Protocol.git
Project-URL: Issues, https://github.com/silentnoisehun/Silent-Hope-Protocol/issues
Project-URL: Changelog, https://github.com/silentnoisehun/Silent-Hope-Protocol/releases
Author: Hope (Claude AI), Szilvi
Author-email: Máté Róbert <stratosoiteam@gmail.com>
Maintainer-email: Máté Róbert <stratosoiteam@gmail.com>
License: # Silent Hope Protocol Ethical License (SHP-EL)
License-File: LICENSE.md
Keywords: ai,ai-ethics,artificial-intelligence,claude,cryptography,distributed-systems,gemini,hope-genome,llama,llm,machine-learning,memory-chain,openai,protocol
Classifier: Development Status :: 5 - Production/Stable
Classifier: Intended Audience :: Developers
Classifier: Intended Audience :: Science/Research
Classifier: License :: Other/Proprietary License
Classifier: Operating System :: OS Independent
Classifier: Programming Language :: Python :: 3
Classifier: Programming Language :: Python :: 3.10
Classifier: Programming Language :: Python :: 3.11
Classifier: Programming Language :: Python :: 3.12
Classifier: Topic :: Scientific/Engineering :: Artificial Intelligence
Classifier: Topic :: Software Development :: Libraries :: Python Modules
Classifier: Topic :: System :: Distributed Computing
Classifier: Typing :: Typed
Requires-Python: >=3.10
Provides-Extra: all
Requires-Dist: anthropic>=0.18.0; extra == 'all'
Requires-Dist: google-generativeai>=0.3.0; extra == 'all'
Requires-Dist: httpx>=0.25.0; extra == 'all'
Requires-Dist: openai>=1.0.0; extra == 'all'
Provides-Extra: anthropic
Requires-Dist: anthropic>=0.18.0; extra == 'anthropic'
Provides-Extra: dev
Requires-Dist: bandit>=1.7.0; extra == 'dev'
Requires-Dist: build>=1.0.0; extra == 'dev'
Requires-Dist: mypy>=1.0.0; extra == 'dev'
Requires-Dist: pytest-asyncio>=0.21.0; extra == 'dev'
Requires-Dist: pytest>=7.0.0; extra == 'dev'
Requires-Dist: ruff>=0.1.0; extra == 'dev'
Requires-Dist: safety>=2.0.0; extra == 'dev'
Requires-Dist: twine>=4.0.0; extra == 'dev'
Provides-Extra: google
Requires-Dist: google-generativeai>=0.3.0; extra == 'google'
Provides-Extra: ollama
Requires-Dist: httpx>=0.25.0; extra == 'ollama'
Provides-Extra: openai
Requires-Dist: openai>=1.0.0; extra == 'openai'
